hexafonter.py
hexafonter-0.1.2.dist-info/entry_points.txt
hexafonter-0.1.2.dist-info/LICENSE.MIT
hexafonter-0.1.2.dist-info/WHEEL
hexafonter-0.1.2.dist-info/METADATA
hexafonter-0.1.2.dist-info/RECORD
