Metadata-Version: 2.1
Name: hexafonter
Version: 0.1.2
Summary: Generate a C font file for a small LCD from a PNG image
Author-email: Petr Viktorin <encukou@gmail.com>
Requires-Python: >=3.6
Classifier: License :: OSI Approved :: MIT License
Requires-Dist: pypng
Project-URL: Source, https://github.com/encukou/hexafonter
